django_grpc_framework_plus/__init__.py
django_grpc_framework_plus/apps.py
django_grpc_framework_plus/generics.py
django_grpc_framework_plus/mixins.py
django_grpc_framework_plus/proto_serializers.py
django_grpc_framework_plus/services.py
django_grpc_framework_plus/settings.py
django_grpc_framework_plus/signals.py
django_grpc_framework_plus/test.py
django_grpc_framework_plus/management/__init__.py
django_grpc_framework_plus/management/commands/__init__.py
django_grpc_framework_plus/management/commands/generateproto.py
django_grpc_framework_plus/management/commands/grpcrunserver.py
django_grpc_framework_plus/protobuf/__init__.py
django_grpc_framework_plus/protobuf/generators.py
django_grpc_framework_plus/protobuf/json_format.py
django_grpc_framework_plus/utils/__init__.py
django_grpc_framework_plus/utils/model_meta.py
django_grpc_framework_plus-0.3.0.dist-info/licenses/LICENSE
django_grpc_framework_plus-0.3.0.dist-info/METADATA
django_grpc_framework_plus-0.3.0.dist-info/WHEEL
django_grpc_framework_plus-0.3.0.dist-info/top_level.txt
django_grpc_framework_plus-0.3.0.dist-info/RECORD
